cellsium/__init__.py
cellsium/__main__.py
cellsium/parameters.py
cellsium/random.py
cellsium/typing.py
cellsium/cli/__init__.py
cellsium/cli/cli.py
cellsium/cli/render/__init__.py
cellsium/cli/simulate/__init__.py
cellsium/cli/training/__init__.py
cellsium/geometry/__init__.py
cellsium/model/__init__.py
cellsium/model/agent.py
cellsium/model/geometry.py
cellsium/model/initialization.py
cellsium/output/__init__.py
cellsium/output/all.py
cellsium/output/gt.py
cellsium/output/mesh.py
cellsium/output/plot.py
cellsium/output/render.py
cellsium/output/serialization.py
cellsium/output/svg.py
cellsium/output/xml.py
cellsium/simulation/__init__.py
cellsium/simulation/simulator.py
cellsium/simulation/placement/__init__.py
cellsium/simulation/placement/base.py
cellsium/simulation/placement/pybox2d.py
cellsium/simulation/placement/pymunk.py
cellsium/tests/__init__.py
cellsium/tests/__main__.py
cellsium/tests/cell_test.py
cellsium/tests/cli_calls_test.py
cellsium/tests/conftest.py
cellsium/tests/doctest_test.py
cellsium/tests/generate_dxf_file.py
cellsium/tests/geometry_test.py
cellsium/tests/misc_test.py
cellsium/tests/output_test.py
cellsium/tests/simulator_test.py
cellsium-1.0.0.dist-info/LICENSE.rst
cellsium-1.0.0.dist-info/WHEEL
cellsium-1.0.0.dist-info/METADATA
cellsium-1.0.0.dist-info/RECORD
