Metadata-Version: 2.1
Name: cellsium
Version: 1.0.0
Summary: CellSium – Cell Simulator for microfluidic microcolonies
Author-email: "Christian C. Sachs" <c.sachs@fz-juelich.de>
Classifier: Development Status :: 4 - Beta
Classifier: Environment :: Console
Classifier: Intended Audience :: Science/Research
Classifier: License :: OSI Approved :: BSD License
Classifier: Operating System :: POSIX
Classifier: Operating System :: POSIX :: Linux
Classifier: Operating System :: MacOS :: MacOS X
Classifier: Operating System :: Microsoft :: Windows
Classifier: Programming Language :: Python :: 3
Classifier: Programming Language :: Python :: 3.8
Classifier: Programming Language :: Python :: 3.9
Classifier: Topic :: Scientific/Engineering :: Bio-Informatics
Classifier: Topic :: Scientific/Engineering :: Image Recognition
Requires-Dist: numpy>=1.17
Requires-Dist: scipy
Requires-Dist: matplotlib
Requires-Dist: tunable
Requires-Dist: jsonpickle
Requires-Dist: tqdm
Requires-Dist: pymunk
Requires-Dist: box2d
Requires-Dist: opencv-python
Requires-Dist: tifffile
Requires-Dist: roifile
Requires-Dist: numpy-stl
Requires-Dist: ezdxf
Requires-Dist: black ; extra == "check"
Requires-Dist: isort ; extra == "check"
Requires-Dist: pyproject-flake8 ; extra == "check"
Requires-Dist: pylint ; extra == "check"
Requires-Dist: sphinx ; extra == "doc"
Requires-Dist: sphinx-rtd-theme ; extra == "doc"
Requires-Dist: pytest ; extra == "test"
Requires-Dist: pytest-cov ; extra == "test"
Project-URL: Source, https://github.com/modsim/cellsium
Provides-Extra: check
Provides-Extra: doc
Provides-Extra: test
